reinforced_lib/__init__.py
reinforced_lib/rlib.py
reinforced_lib/agents/__init__.py
reinforced_lib/agents/base_agent.py
reinforced_lib/agents/deep/__init__.py
reinforced_lib/agents/deep/ddpg.py
reinforced_lib/agents/deep/ddqn.py
reinforced_lib/agents/deep/dqn.py
reinforced_lib/agents/deep/expected_sarsa.py
reinforced_lib/agents/deep/ppo_continuous.py
reinforced_lib/agents/deep/ppo_discrete.py
reinforced_lib/agents/mab/__init__.py
reinforced_lib/agents/mab/e_greedy.py
reinforced_lib/agents/mab/exp3.py
reinforced_lib/agents/mab/lognormal_thompson_sampling.py
reinforced_lib/agents/mab/normal_thompson_sampling.py
reinforced_lib/agents/mab/softmax.py
reinforced_lib/agents/mab/thompson_sampling.py
reinforced_lib/agents/mab/ucb.py
reinforced_lib/agents/mab/scheduler/__init__.py
reinforced_lib/agents/mab/scheduler/random.py
reinforced_lib/agents/mab/scheduler/round_robin.py
reinforced_lib/agents/neuro/__init__.py
reinforced_lib/agents/neuro/evosax.py
reinforced_lib/experimental/__init__.py
reinforced_lib/experimental/masked.py
reinforced_lib/exts/__init__.py
reinforced_lib/exts/base_ext.py
reinforced_lib/exts/basic_mab.py
reinforced_lib/exts/gymnasium.py
reinforced_lib/exts/gymnasium_vectorized.py
reinforced_lib/exts/utils.py
reinforced_lib/logs/__init__.py
reinforced_lib/logs/base_logger.py
reinforced_lib/logs/csv_logger.py
reinforced_lib/logs/logs_observer.py
reinforced_lib/logs/plots_logger.py
reinforced_lib/logs/stdout_logger.py
reinforced_lib/logs/tb_logger.py
reinforced_lib/logs/wandb_logger.py
reinforced_lib/utils/__init__.py
reinforced_lib/utils/exceptions.py
reinforced_lib/utils/experience_replay.py
reinforced_lib/utils/jax_utils.py
reinforced_lib/utils/particle_filter.py
reinforced_lib/utils/rollout_buffer.py
reinforced_lib-2.0.0.dist-info/licenses/LICENSE
reinforced_lib-2.0.0.dist-info/METADATA
reinforced_lib-2.0.0.dist-info/WHEEL
reinforced_lib-2.0.0.dist-info/top_level.txt
reinforced_lib-2.0.0.dist-info/RECORD
