Metadata-Version: 2.4
Name: reinforced-lib
Version: 2.0.0
Summary: Reinforcement learning library
Author-email: Maksymilian Wojnar <mwojnar@agh.edu.pl>, Wojciech Ciężobka <wciezobka@agh.edu.pl>, Krzysztof Rusek <krusek@agh.edu.pl>
License: Attribution 4.0 International
Keywords: deep-reinforcement-learning,jax,library,machine-learning,reinforcement-learning
Classifier: Development Status :: 5 - Production/Stable
Classifier: Intended Audience :: Developers
Classifier: Intended Audience :: Education
Classifier: Intended Audience :: Science/Research
Classifier: Programming Language :: Python :: 3
Classifier: Programming Language :: Python :: 3.12
Classifier: Topic :: Scientific/Engineering :: Artificial Intelligence
Classifier: Typing :: Typed
Requires-Python: <4,>=3.12
License-File: LICENSE
Requires-Dist: cloudpickle~=3.1.1
Requires-Dist: evosax~=0.2.0
Requires-Dist: gymnasium~=1.2.1
Requires-Dist: jax-ai-stack~=2025.4.9
Requires-Dist: lz4~=4.4.4
Requires-Dist: matplotlib~=3.10.6
Requires-Dist: tensorboardX~=2.6.4
Requires-Dist: wandb~=0.22.0
Provides-Extra: docs
Requires-Dist: sphinx~=8.2.3; extra == "docs"
Requires-Dist: sphinx-rtd-theme~=3.0.2; extra == "docs"
Provides-Extra: full
Requires-Dist: joblib~=1.5.2; extra == "full"
Requires-Dist: pygame~=2.6.1; extra == "full"
Requires-Dist: seaborn~=0.13.2; extra == "full"
Requires-Dist: tensorflow~=2.19.1; extra == "full"
Dynamic: license-file
